envaml/.env.sh
envaml/__init__.py
envaml/converter.py
envaml/tests/generate_env_yaml.py
envaml-0.1.5.dist-info/METADATA
envaml-0.1.5.dist-info/WHEEL
envaml-0.1.5.dist-info/entry_points.txt
envaml-0.1.5.dist-info/licenses/LICENSE.txt
envaml-0.1.5.dist-info/RECORD
